{"playersMatches":[{"match_id":6868392010,"account_id":2,"player_slot":1,"win":0,"profile":{"account_id":2,"personaname":"unknown","avatarfull":"https://steamuserimages-a.akamaihd.net/ugc/885384897182110030/F095539864AC9E94AE5236E04C8CA7C2725BCEFF/","loccountrycode":"SOUTH AMERICA"}},{"match_id":6868392010,"account_id":129,"player_slot":128,"win":1,"profile":{"account_id":129,"personaname":"unknown","avatarfull":"https://steamuserimages-a.akamaihd.net/ugc/885384897182110030/F095539864AC9E94AE5236E04C8CA7C2725BCEFF/","loccountrycode":"SOUTH AMERICA"}},{"match_id":6868392010,"account_id":133,"player_slot":132,"win":1,"profile":{"account_id":133,"personaname":"unknown","avatarfull":"https://steamuserimages-a.akamaihd.net/ugc/885384897182110030/F095539864AC9E94AE5236E04C8CA7C2725BCEFF/","loccountrycode":"SOUTH AMERICA"}},{"match_id":6868392010,"account_id":28490738,"player_slot":2,"win":0,"profile":{"account_id":28490738,"personaname":"♥Get Rekt™","avatarfull":"https://avatars.akamai.steamstatic.com/ec2d6444c58b14ded8b0d8bc390e69009116f33e_full.jpg","loccountrycode":"SOUTH AMERICA"}},{"match_id":6868392010,"account_id":61895929,"player_slot":131,"win":1,"profile":{"account_id":61895929,"personaname":"kimzerapqp","avatarfull":"https://avatars.akamai.steamstatic.com/3804cd416262ee8934b63067ad9f63df81115e2e_full.jpg","loccountrycode":"SOUTH AMERICA"}},{"match_id":6868392010,"account_id":87683422,"player_slot":3,"win":0,"profile":{"account_id":87683422,"personaname":"Avatar | dotatryhard.vercel.app","avatarfull":"https://avatars.akamai.steamstatic.com/f08b34efd0bf0b6cd6505b10a21ab41385932873_full.jpg","loccountrycode":"SOUTH AMERICA"}},{"match_id":6868392010,"account_id":100592368,"player_slot":130,"win":1,"profile":{"account_id":100592368,"personaname":"✪ CH ✪","avatarfull":"https://avatars.akamai.steamstatic.com/dc64eb8709bbd352b14e6232768d68f5f1256ebd_full.jpg","loccountrycode":"SOUTH AMERICA"}},{"match_id":6868392010,"account_id":123161333,"player_slot":129,"win":1,"profile":{"account_id":123161333,"personaname":"TheLG","avatarfull":"https://avatars.akamai.steamstatic.com/7a7626ccc78e0fb98a99d639eb9160f585a6fb15_full.jpg","loccountrycode":"SOUTH AMERICA"}},{"match_id":6868392010,"account_id":130155428,"player_slot":4,"win":0,"profile":{"account_id":130155428,"personaname":"FonteBoa","avatarfull":"https://avatars.akamai.steamstatic.com/5c1713360b04999b1ed70091521533597a100b5d_full.jpg","loccountrycode":"SOUTH AMERICA"}},{"match_id":6868392010,"account_id":144957188,"player_slot":0,"win":0,"profile":{"account_id":144957188,"personaname":"thor gordo","avatarfull":"https://avatars.akamai.steamstatic.com/46be299c9a970e70b858198349c7a8e779788a1f_full.jpg","loccountrycode":"SOUTH AMERICA"}},{"match_id":6868427177,"account_id":4,"player_slot":3,"win":0,"profile":{"account_id":4,"personaname":"unknown","avatarfull":"https://steamuserimages-a.akamaihd.net/ugc/885384897182110030/F095539864AC9E94AE5236E04C8CA7C2725BCEFF/","loccountrycode":"SOUTH AMERICA"}},{"match_id":6868427177,"account_id":5,"player_slot":4,"win":0,"profile":{"account_id":5,"personaname":"unknown","avatarfull":"https://steamuserimages-a.akamaihd.net/ugc/885384897182110030/F095539864AC9E94AE5236E04C8CA7C2725BCEFF/","loccountrycode":"SOUTH AMERICA"}},{"match_id":6868427177,"account_id":129,"player_slot":128,"win":1,"profile":{"account_id":129,"personaname":"unknown","avatarfull":"https://steamuserimages-a.akamaihd.net/ugc/885384897182110030/F095539864AC9E94AE5236E04C8CA7C2725BCEFF/","loccountrycode":"SOUTH AMERICA"}},{"match_id":6868427177,"account_id":28490738,"player_slot":1,"win":0,"profile":{"account_id":28490738,"personaname":"♥Get Rekt™","avatarfull":"https://avatars.akamai.steamstatic.com/ec2d6444c58b14ded8b0d8bc390e69009116f33e_full.jpg","loccountrycode":"SOUTH AMERICA"}},{"match_id":6868427177,"account_id":61895929,"player_slot":131,"win":1,"profile":{"account_id":61895929,"personaname":"kimzerapqp","avatarfull":"https://avatars.akamai.steamstatic.com/3804cd416262ee8934b63067ad9f63df81115e2e_full.jpg","loccountrycode":"SOUTH AMERICA"}},{"match_id":6868427177,"account_id":100592368,"player_slot":130,"win":1,"profile":{"account_id":100592368,"personaname":"✪ CH ✪","avatarfull":"https://avatars.akamai.steamstatic.com/dc64eb8709bbd352b14e6232768d68f5f1256ebd_full.jpg","loccountrycode":"SOUTH AMERICA"}},{"match_id":6868427177,"account_id":123161333,"player_slot":129,"win":1,"profile":{"account_id":123161333,"personaname":"TheLG","avatarfull":"https://avatars.akamai.steamstatic.com/7a7626ccc78e0fb98a99d639eb9160f585a6fb15_full.jpg","loccountrycode":"SOUTH AMERICA"}},{"match_id":6868427177,"account_id":144957188,"player_slot":0,"win":0,"profile":{"account_id":144957188,"personaname":"thor gordo","avatarfull":"https://avatars.akamai.steamstatic.com/46be299c9a970e70b858198349c7a8e779788a1f_full.jpg","loccountrycode":"SOUTH AMERICA"}},{"match_id":6868427177,"account_id":153686920,"player_slot":2,"win":0,"profile":{"account_id":153686920,"personaname":"Kaugummi","avatarfull":"https://avatars.akamai.steamstatic.com/e902262610db5b74f1a391131c80909f0cad7e2c_full.jpg","loccountrycode":"SOUTH AMERICA"}},{"match_id":6868427177,"account_id":428934650,"player_slot":132,"win":1,"profile":{"account_id":428934650,"personaname":"♠• ❈LevBulgaro❈ •♠","avatarfull":"https://avatars.akamai.steamstatic.com/9cb33145215191bdf388e5f32538371c4802f88f_full.jpg","loccountrycode":"SOUTH AMERICA"}},{"match_id":6881377114,"account_id":1,"player_slot":0,"win":1,"profile":{"account_id":1,"personaname":"unknown","avatarfull":"https://steamuserimages-a.akamaihd.net/ugc/885384897182110030/F095539864AC9E94AE5236E04C8CA7C2725BCEFF/","loccountrycode":"SOUTH AMERICA"}},{"match_id":6881377114,"account_id":2,"player_slot":1,"win":1,"profile":{"account_id":2,"personaname":"unknown","avatarfull":"https://steamuserimages-a.akamaihd.net/ugc/885384897182110030/F095539864AC9E94AE5236E04C8CA7C2725BCEFF/","loccountrycode":"SOUTH AMERICA"}},{"match_id":6881377114,"account_id":5,"player_slot":4,"win":1,"profile":{"account_id":5,"personaname":"unknown","avatarfull":"https://steamuserimages-a.akamaihd.net/ugc/885384897182110030/F095539864AC9E94AE5236E04C8CA7C2725BCEFF/","loccountrycode":"SOUTH AMERICA"}},{"match_id":6881377114,"account_id":129,"player_slot":128,"win":0,"profile":{"account_id":129,"personaname":"unknown","avatarfull":"https://steamuserimages-a.akamaihd.net/ugc/885384897182110030/F095539864AC9E94AE5236E04C8CA7C2725BCEFF/","loccountrycode":"SOUTH AMERICA"}},{"match_id":6881377114,"account_id":130,"player_slot":129,"win":0,"profile":{"account_id":130,"personaname":"unknown","avatarfull":"https://steamuserimages-a.akamaihd.net/ugc/885384897182110030/F095539864AC9E94AE5236E04C8CA7C2725BCEFF/","loccountrycode":"SOUTH AMERICA"}},{"match_id":6881377114,"account_id":132,"player_slot":131,"win":0,"profile":{"account_id":132,"personaname":"unknown","avatarfull":"https://steamuserimages-a.akamaihd.net/ugc/885384897182110030/F095539864AC9E94AE5236E04C8CA7C2725BCEFF/","loccountrycode":"SOUTH AMERICA"}},{"match_id":6881377114,"account_id":100592368,"player_slot":2,"win":1,"profile":{"account_id":100592368,"personaname":"✪ CH ✪","avatarfull":"https://avatars.akamai.steamstatic.com/dc64eb8709bbd352b14e6232768d68f5f1256ebd_full.jpg","loccountrycode":"SOUTH AMERICA"}},{"match_id":6881377114,"account_id":123161333,"player_slot":3,"win":1,"profile":{"account_id":123161333,"personaname":"TheLG","avatarfull":"https://avatars.akamai.steamstatic.com/7a7626ccc78e0fb98a99d639eb9160f585a6fb15_full.jpg","loccountrycode":"SOUTH AMERICA"}},{"match_id":6881377114,"account_id":909288572,"player_slot":132,"win":0,"profile":{"account_id":909288572,"personaname":"☣CyberLek❀","avatarfull":"https://avatars.akamai.steamstatic.com/2802d38f5cc6a0dd207c5381f7f5aea989135b08_full.jpg","loccountrycode":"SOUTH AMERICA"}},{"match_id":6881377114,"account_id":1042006985,"player_slot":130,"win":0,"profile":{"account_id":1042006985,"personaname":"mata collas","avatarfull":"https://avatars.akamai.steamstatic.com/2e3c568674aaf64f50142935674cc1bb10ac8d34_full.jpg","loccountrycode":"SOUTH AMERICA"}},{"match_id":6906828666,"account_id":5,"player_slot":4,"win":1,"profile":{"account_id":5,"personaname":"unknown","avatarfull":"https://steamuserimages-a.akamaihd.net/ugc/885384897182110030/F095539864AC9E94AE5236E04C8CA7C2725BCEFF/","loccountrycode":"SOUTH AMERICA"}},{"match_id":6906828666,"account_id":67656344,"player_slot":132,"win":0,"profile":{"account_id":67656344,"personaname":"Cout","avatarfull":"https://avatars.akamai.steamstatic.com/f28b55b7f59e8634673f24e9deb840f173d7eec1_full.jpg","loccountrycode":"SOUTH AMERICA"}},{"match_id":6906828666,"account_id":86705173,"player_slot":128,"win":0,"profile":{"account_id":86705173,"personaname":"Avenger","avatarfull":"https://avatars.akamai.steamstatic.com/0af1c9bfe1214658a3425d6a930c110b97c66dbf_full.jpg","loccountrycode":"SOUTH AMERICA"}},{"match_id":6906828666,"account_id":86764844,"player_slot":131,"win":0,"profile":{"account_id":86764844,"personaname":"MarMosell","avatarfull":"https://avatars.akamai.steamstatic.com/febfdc238bfee83b2f31ff90d733dc11197fe890_full.jpg","loccountrycode":"SOUTH AMERICA"}},{"match_id":6906828666,"account_id":100592368,"player_slot":1,"win":1,"profile":{"account_id":100592368,"personaname":"✪ CH ✪","avatarfull":"https://avatars.akamai.steamstatic.com/dc64eb8709bbd352b14e6232768d68f5f1256ebd_full.jpg","loccountrycode":"SOUTH AMERICA"}},{"match_id":6906828666,"account_id":123161333,"player_slot":0,"win":1,"profile":{"account_id":123161333,"personaname":"TheLG","avatarfull":"https://avatars.akamai.steamstatic.com/7a7626ccc78e0fb98a99d639eb9160f585a6fb15_full.jpg","loccountrycode":"SOUTH AMERICA"}},{"match_id":6906828666,"account_id":130155428,"player_slot":2,"win":1,"profile":{"account_id":130155428,"personaname":"FonteBoa","avatarfull":"https://avatars.akamai.steamstatic.com/5c1713360b04999b1ed70091521533597a100b5d_full.jpg","loccountrycode":"SOUTH AMERICA"}},{"match_id":6906828666,"account_id":143076863,"player_slot":129,"win":0,"profile":{"account_id":143076863,"personaname":"CaRPi","avatarfull":"https://avatars.akamai.steamstatic.com/1f097d4593e31c8fbbae075978e5983c59f1e33d_full.jpg","loccountrycode":"SOUTH AMERICA"}},{"match_id":6906828666,"account_id":171517256,"player_slot":130,"win":0,"profile":{"account_id":171517256,"personaname":"The Winter Boys","avatarfull":"https://avatars.akamai.steamstatic.com/fb938f9dd7e02cb308d175a1f92cfb81a3e2cda6_full.jpg","loccountrycode":"SOUTH AMERICA"}},{"match_id":6906828666,"account_id":174144666,"player_slot":3,"win":1,"profile":{"account_id":174144666,"personaname":"Kenko","avatarfull":"https://avatars.akamai.steamstatic.com/e4a65eb190f5e30457d9bcddbb502cd55385fe0b_full.jpg","loccountrycode":"SOUTH AMERICA"}},{"match_id":6906963089,"account_id":129,"player_slot":128,"win":0,"profile":{"account_id":129,"personaname":"unknown","avatarfull":"https://steamuserimages-a.akamaihd.net/ugc/885384897182110030/F095539864AC9E94AE5236E04C8CA7C2725BCEFF/","loccountrycode":"SOUTH AMERICA"}},{"match_id":6906963089,"account_id":131,"player_slot":130,"win":0,"profile":{"account_id":131,"personaname":"unknown","avatarfull":"https://steamuserimages-a.akamaihd.net/ugc/885384897182110030/F095539864AC9E94AE5236E04C8CA7C2725BCEFF/","loccountrycode":"SOUTH AMERICA"}},{"match_id":6906963089,"account_id":132,"player_slot":131,"win":0,"profile":{"account_id":132,"personaname":"unknown","avatarfull":"https://steamuserimages-a.akamaihd.net/ugc/885384897182110030/F095539864AC9E94AE5236E04C8CA7C2725BCEFF/","loccountrycode":"SOUTH AMERICA"}},{"match_id":6906963089,"account_id":96268745,"player_slot":4,"win":1,"profile":{"account_id":96268745,"personaname":"WEEZER","avatarfull":"https://avatars.akamai.steamstatic.com/8a22aad4839c7e23e357e7afa4b1f002fe481784_full.jpg","loccountrycode":"SOUTH AMERICA"}},{"match_id":6906963089,"account_id":100592368,"player_slot":0,"win":1,"profile":{"account_id":100592368,"personaname":"✪ CH ✪","avatarfull":"https://avatars.akamai.steamstatic.com/dc64eb8709bbd352b14e6232768d68f5f1256ebd_full.jpg","loccountrycode":"SOUTH AMERICA"}},{"match_id":6906963089,"account_id":123161333,"player_slot":129,"win":0,"profile":{"account_id":123161333,"personaname":"TheLG","avatarfull":"https://avatars.akamai.steamstatic.com/7a7626ccc78e0fb98a99d639eb9160f585a6fb15_full.jpg","loccountrycode":"SOUTH AMERICA"}},{"match_id":6906963089,"account_id":126222462,"player_slot":3,"win":1,"profile":{"account_id":126222462,"personaname":"PanKra","avatarfull":"https://avatars.akamai.steamstatic.com/e688b47d2901be41f1f98ebbe8c7793700b9734b_full.jpg","loccountrycode":"SOUTH AMERICA"}},{"match_id":6906963089,"account_id":130155428,"player_slot":132,"win":0,"profile":{"account_id":130155428,"personaname":"FonteBoa","avatarfull":"https://avatars.akamai.steamstatic.com/5c1713360b04999b1ed70091521533597a100b5d_full.jpg","loccountrycode":"SOUTH AMERICA"}},{"match_id":6906963089,"account_id":234492017,"player_slot":1,"win":1,"profile":{"account_id":234492017,"personaname":"💜 T.tv/Chompini 💜","avatarfull":"https://avatars.akamai.steamstatic.com/9422aa6779387790094950ca63d08ffd4460c3ed_full.jpg","loccountrycode":"SOUTH AMERICA"}},{"match_id":6906963089,"account_id":356551655,"player_slot":2,"win":1,"profile":{"account_id":356551655,"personaname":"SilverDusk","avatarfull":"https://avatars.akamai.steamstatic.com/6011939482ad81d3605eb44ee5ee797c95151825_full.jpg","loccountrycode":"SOUTH AMERICA"}},{"match_id":6906995972,"account_id":2,"player_slot":1,"win":0,"profile":{"account_id":2,"personaname":"unknown","avatarfull":"https://steamuserimages-a.akamaihd.net/ugc/885384897182110030/F095539864AC9E94AE5236E04C8CA7C2725BCEFF/","loccountrycode":"SOUTH AMERICA"}},{"match_id":6906995972,"account_id":5,"player_slot":4,"win":0,"profile":{"account_id":5,"personaname":"unknown","avatarfull":"https://steamuserimages-a.akamaihd.net/ugc/885384897182110030/F095539864AC9E94AE5236E04C8CA7C2725BCEFF/","loccountrycode":"SOUTH AMERICA"}},{"match_id":6906995972,"account_id":131,"player_slot":130,"win":1,"profile":{"account_id":131,"personaname":"unknown","avatarfull":"https://steamuserimages-a.akamaihd.net/ugc/885384897182110030/F095539864AC9E94AE5236E04C8CA7C2725BCEFF/","loccountrycode":"SOUTH AMERICA"}},{"match_id":6906995972,"account_id":132,"player_slot":131,"win":1,"profile":{"account_id":132,"personaname":"unknown","avatarfull":"https://steamuserimages-a.akamaihd.net/ugc/885384897182110030/F095539864AC9E94AE5236E04C8CA7C2725BCEFF/","loccountrycode":"SOUTH AMERICA"}},{"match_id":6906995972,"account_id":100592368,"player_slot":132,"win":1,"profile":{"account_id":100592368,"personaname":"✪ CH ✪","avatarfull":"https://avatars.akamai.steamstatic.com/dc64eb8709bbd352b14e6232768d68f5f1256ebd_full.jpg","loccountrycode":"SOUTH AMERICA"}},{"match_id":6906995972,"account_id":123161333,"player_slot":129,"win":1,"profile":{"account_id":123161333,"personaname":"TheLG","avatarfull":"https://avatars.akamai.steamstatic.com/7a7626ccc78e0fb98a99d639eb9160f585a6fb15_full.jpg","loccountrycode":"SOUTH AMERICA"}},{"match_id":6906995972,"account_id":130155428,"player_slot":128,"win":1,"profile":{"account_id":130155428,"personaname":"FonteBoa","avatarfull":"https://avatars.akamai.steamstatic.com/5c1713360b04999b1ed70091521533597a100b5d_full.jpg","loccountrycode":"SOUTH AMERICA"}},{"match_id":6906995972,"account_id":147868186,"player_slot":0,"win":0,"profile":{"account_id":147868186,"personaname":"宝可梦-杂技车","avatarfull":"https://avatars.akamai.steamstatic.com/08f5adb4a0c0437589a2849305ecd7a9b8461749_full.jpg","loccountrycode":"SOUTH AMERICA"}},{"match_id":6906995972,"account_id":171055263,"player_slot":3,"win":0,"profile":{"account_id":171055263,"personaname":"Yan","avatarfull":"https://avatars.akamai.steamstatic.com/457ed01689daa81186b8949ff3f810fc45059cd5_full.jpg","loccountrycode":"SOUTH AMERICA"}},{"match_id":6906995972,"account_id":224305158,"player_slot":2,"win":0,"profile":{"account_id":224305158,"personaname":"鸡儿硬邦邦","avatarfull":"https://avatars.akamai.steamstatic.com/cfdbea20c0e2b111e6ed5f760cb02b9f4e0ab87c_full.jpg","loccountrycode":"SOUTH AMERICA"}},{"match_id":6917247754,"account_id":3,"player_slot":2,"win":0,"profile":{"account_id":3,"personaname":"unknown","avatarfull":"https://steamuserimages-a.akamaihd.net/ugc/885384897182110030/F095539864AC9E94AE5236E04C8CA7C2725BCEFF/","loccountrycode":"SOUTH AMERICA"}},{"match_id":6917247754,"account_id":59262103,"player_slot":132,"win":1,"profile":{"account_id":59262103,"personaname":"-Kmz'","avatarfull":"https://avatars.akamai.steamstatic.com/92aedeb8db783b2d03acd799cfc87ae3390e02e9_full.jpg","loccountrycode":"SOUTH AMERICA"}},{"match_id":6917247754,"account_id":86872897,"player_slot":0,"win":0,"profile":{"account_id":86872897,"personaname":"Dae wae","avatarfull":"https://avatars.akamai.steamstatic.com/1f5bd830895b9de2314c58827585afbf6b37ceb0_full.jpg","loccountrycode":"SOUTH AMERICA"}},{"match_id":6917247754,"account_id":100592368,"player_slot":131,"win":1,"profile":{"account_id":100592368,"personaname":"✪ CH ✪","avatarfull":"https://avatars.akamai.steamstatic.com/dc64eb8709bbd352b14e6232768d68f5f1256ebd_full.jpg","loccountrycode":"SOUTH AMERICA"}},{"match_id":6917247754,"account_id":123161333,"player_slot":130,"win":1,"profile":{"account_id":123161333,"personaname":"TheLG","avatarfull":"https://avatars.akamai.steamstatic.com/7a7626ccc78e0fb98a99d639eb9160f585a6fb15_full.jpg","loccountrycode":"SOUTH AMERICA"}},{"match_id":6917247754,"account_id":130155428,"player_slot":129,"win":1,"profile":{"account_id":130155428,"personaname":"FonteBoa","avatarfull":"https://avatars.akamai.steamstatic.com/5c1713360b04999b1ed70091521533597a100b5d_full.jpg","loccountrycode":"SOUTH AMERICA"}},{"match_id":6917247754,"account_id":147868186,"player_slot":1,"win":0,"profile":{"account_id":147868186,"personaname":"宝可梦-杂技车","avatarfull":"https://avatars.akamai.steamstatic.com/08f5adb4a0c0437589a2849305ecd7a9b8461749_full.jpg","loccountrycode":"SOUTH AMERICA"}},{"match_id":6917247754,"account_id":171055263,"player_slot":3,"win":0,"profile":{"account_id":171055263,"personaname":"Yan","avatarfull":"https://avatars.akamai.steamstatic.com/457ed01689daa81186b8949ff3f810fc45059cd5_full.jpg","loccountrycode":"SOUTH AMERICA"}},{"match_id":6917247754,"account_id":202039844,"player_slot":128,"win":1,"profile":{"account_id":202039844,"personaname":"§îr §l@¥ër","avatarfull":"https://avatars.akamai.steamstatic.com/735b50d542aa21b602e2291a6ebe5fe6364b672c_full.jpg","loccountrycode":"SOUTH AMERICA"}},{"match_id":6917247754,"account_id":224305158,"player_slot":4,"win":0,"profile":{"account_id":224305158,"personaname":"鸡儿硬邦邦","avatarfull":"https://avatars.akamai.steamstatic.com/cfdbea20c0e2b111e6ed5f760cb02b9f4e0ab87c_full.jpg","loccountrycode":"SOUTH AMERICA"}},{"match_id":6930237390,"account_id":5,"player_slot":4,"win":1,"profile":{"account_id":5,"personaname":"unknown","avatarfull":"https://steamuserimages-a.akamaihd.net/ugc/885384897182110030/F095539864AC9E94AE5236E04C8CA7C2725BCEFF/","loccountrycode":"SOUTH AMERICA"}},{"match_id":6930237390,"account_id":129,"player_slot":128,"win":0,"profile":{"account_id":129,"personaname":"unknown","avatarfull":"https://steamuserimages-a.akamaihd.net/ugc/885384897182110030/F095539864AC9E94AE5236E04C8CA7C2725BCEFF/","loccountrycode":"SOUTH AMERICA"}},{"match_id":6930237390,"account_id":81035765,"player_slot":132,"win":0,"profile":{"account_id":81035765,"personaname":"DOTAMARRO","avatarfull":"https://avatars.akamai.steamstatic.com/2c45989b6bb7045e1c4414b574714fe632d2a53f_full.jpg","loccountrycode":"SOUTH AMERICA"}},{"match_id":6930237390,"account_id":100592368,"player_slot":2,"win":1,"profile":{"account_id":100592368,"personaname":"✪ CH ✪","avatarfull":"https://avatars.akamai.steamstatic.com/dc64eb8709bbd352b14e6232768d68f5f1256ebd_full.jpg","loccountrycode":"SOUTH AMERICA"}},{"match_id":6930237390,"account_id":106042423,"player_slot":129,"win":0,"profile":{"account_id":106042423,"personaname":"EternalSorrow","avatarfull":"https://avatars.akamai.steamstatic.com/f119da8b1bb3c14b1b9dd9e96dd7765f53e02fc9_full.jpg","loccountrycode":"SOUTH AMERICA"}},{"match_id":6930237390,"account_id":113021094,"player_slot":130,"win":0,"profile":{"account_id":113021094,"personaname":"SGT Skinner","avatarfull":"https://avatars.akamai.steamstatic.com/ddb5aac71db60d585d9a5cc265f28baa53cbfc6e_full.jpg","loccountrycode":"SOUTH AMERICA"}},{"match_id":6930237390,"account_id":114914429,"player_slot":131,"win":0,"profile":{"account_id":114914429,"personaname":"Esu_Wishmaster","avatarfull":"https://avatars.akamai.steamstatic.com/fef49e7fa7e1997310d705b2a6158ff8dc1cdfeb_full.jpg","loccountrycode":"SOUTH AMERICA"}},{"match_id":6930237390,"account_id":114915830,"player_slot":0,"win":1,"profile":{"account_id":114915830,"personaname":"HappyJesus","avatarfull":"https://avatars.akamai.steamstatic.com/15d69ea5231ca5d81b18bbba375db1d705aca8b6_full.jpg","loccountrycode":"SOUTH AMERICA"}},{"match_id":6930237390,"account_id":123161333,"player_slot":3,"win":1,"profile":{"account_id":123161333,"personaname":"TheLG","avatarfull":"https://avatars.akamai.steamstatic.com/7a7626ccc78e0fb98a99d639eb9160f585a6fb15_full.jpg","loccountrycode":"SOUTH AMERICA"}},{"match_id":6930237390,"account_id":130155428,"player_slot":1,"win":1,"profile":{"account_id":130155428,"personaname":"FonteBoa","avatarfull":"https://avatars.akamai.steamstatic.com/5c1713360b04999b1ed70091521533597a100b5d_full.jpg","loccountrycode":"SOUTH AMERICA"}},{"match_id":6938342150,"account_id":2,"player_slot":1,"win":1,"profile":{"account_id":2,"personaname":"unknown","avatarfull":"https://steamuserimages-a.akamaihd.net/ugc/885384897182110030/F095539864AC9E94AE5236E04C8CA7C2725BCEFF/","loccountrycode":"SOUTH AMERICA"}},{"match_id":6938342150,"account_id":130,"player_slot":129,"win":0,"profile":{"account_id":130,"personaname":"unknown","avatarfull":"https://steamuserimages-a.akamaihd.net/ugc/885384897182110030/F095539864AC9E94AE5236E04C8CA7C2725BCEFF/","loccountrycode":"SOUTH AMERICA"}},{"match_id":6938342150,"account_id":133,"player_slot":132,"win":0,"profile":{"account_id":133,"personaname":"unknown","avatarfull":"https://steamuserimages-a.akamaihd.net/ugc/885384897182110030/F095539864AC9E94AE5236E04C8CA7C2725BCEFF/","loccountrycode":"SOUTH AMERICA"}},{"match_id":6938342150,"account_id":87067897,"player_slot":2,"win":1,"profile":{"account_id":87067897,"personaname":"Balgus","avatarfull":"https://avatars.akamai.steamstatic.com/d0e559d0fb05b1f4c6d262356c19ea01c5e7570d_full.jpg","loccountrycode":"SOUTH AMERICA"}},{"match_id":6938342150,"account_id":100592368,"player_slot":4,"win":1,"profile":{"account_id":100592368,"personaname":"✪ CH ✪","avatarfull":"https://avatars.akamai.steamstatic.com/dc64eb8709bbd352b14e6232768d68f5f1256ebd_full.jpg","loccountrycode":"SOUTH AMERICA"}},{"match_id":6938342150,"account_id":126902905,"player_slot":0,"win":1,"profile":{"account_id":126902905,"personaname":"Valyth","avatarfull":"https://avatars.akamai.steamstatic.com/4b1dbcbb6a54b63c5221c91ebedb7118f293bd4b_full.jpg","loccountrycode":"SOUTH AMERICA"}},{"match_id":6938342150,"account_id":144957188,"player_slot":3,"win":1,"profile":{"account_id":144957188,"personaname":"thor gordo","avatarfull":"https://avatars.akamai.steamstatic.com/46be299c9a970e70b858198349c7a8e779788a1f_full.jpg","loccountrycode":"SOUTH AMERICA"}},{"match_id":6938342150,"account_id":148185817,"player_slot":130,"win":0,"profile":{"account_id":148185817,"personaname":"Grim J0ker","avatarfull":"https://avatars.akamai.steamstatic.com/f3d05db4d8557efbcdbfb337f4176abe9fcb5c1b_full.jpg","loccountrycode":"SOUTH AMERICA"}},{"match_id":6938342150,"account_id":148446901,"player_slot":128,"win":0,"profile":{"account_id":148446901,"personaname":"Patao Guerreiro","avatarfull":"https://avatars.akamai.steamstatic.com/ca5413ab68e7bc24517b4d69a100c77b16a721ce_full.jpg","loccountrycode":"SOUTH AMERICA"}},{"match_id":6938342150,"account_id":183666104,"player_slot":131,"win":0,"profile":{"account_id":183666104,"personaname":"PROFESSOR SAFADÃO","avatarfull":"https://avatars.akamai.steamstatic.com/7cb8c96d987a58cbfe37f71d7506b5eb5fef6ccd_full.jpg","loccountrycode":"SOUTH AMERICA"}},{"match_id":6938422211,"account_id":1,"player_slot":0,"win":1,"profile":{"account_id":1,"personaname":"unknown","avatarfull":"https://steamuserimages-a.akamaihd.net/ugc/885384897182110030/F095539864AC9E94AE5236E04C8CA7C2725BCEFF/","loccountrycode":"SOUTH AMERICA"}},{"match_id":6938422211,"account_id":131,"player_slot":130,"win":0,"profile":{"account_id":131,"personaname":"unknown","avatarfull":"https://steamuserimages-a.akamaihd.net/ugc/885384897182110030/F095539864AC9E94AE5236E04C8CA7C2725BCEFF/","loccountrycode":"SOUTH AMERICA"}},{"match_id":6938422211,"account_id":61895929,"player_slot":2,"win":1,"profile":{"account_id":61895929,"personaname":"kimzerapqp","avatarfull":"https://avatars.akamai.steamstatic.com/3804cd416262ee8934b63067ad9f63df81115e2e_full.jpg","loccountrycode":"SOUTH AMERICA"}},{"match_id":6938422211,"account_id":87067897,"player_slot":1,"win":1,"profile":{"account_id":87067897,"personaname":"Balgus","avatarfull":"https://avatars.akamai.steamstatic.com/d0e559d0fb05b1f4c6d262356c19ea01c5e7570d_full.jpg","loccountrycode":"SOUTH AMERICA"}},{"match_id":6938422211,"account_id":100532405,"player_slot":132,"win":0,"profile":{"account_id":100532405,"personaname":"SacoDivine","avatarfull":"https://avatars.akamai.steamstatic.com/12c43192f0a69eb7c93f5bf76559f021f20a258c_full.jpg","loccountrycode":"SOUTH AMERICA"}},{"match_id":6938422211,"account_id":100592368,"player_slot":3,"win":1,"profile":{"account_id":100592368,"personaname":"✪ CH ✪","avatarfull":"https://avatars.akamai.steamstatic.com/dc64eb8709bbd352b14e6232768d68f5f1256ebd_full.jpg","loccountrycode":"SOUTH AMERICA"}},{"match_id":6938422211,"account_id":102219516,"player_slot":129,"win":0,"profile":{"account_id":102219516,"personaname":"-M- ®","avatarfull":"https://avatars.akamai.steamstatic.com/8253b2b2d0c93738f15168b8f0755ba5262afcf8_full.jpg","loccountrycode":"SOUTH AMERICA"}},{"match_id":6938422211,"account_id":109039564,"player_slot":131,"win":0,"profile":{"account_id":109039564,"personaname":"Guts","avatarfull":"https://avatars.akamai.steamstatic.com/9844c07c4e2806bf9172a409b9c3a3dc31d56d6b_full.jpg","loccountrycode":"SOUTH AMERICA"}},{"match_id":6938422211,"account_id":122844733,"player_slot":128,"win":0,"profile":{"account_id":122844733,"personaname":"Hefestos.D","avatarfull":"https://avatars.akamai.steamstatic.com/2aa29a0f1219a971644c46f27ace169644979535_full.jpg","loccountrycode":"SOUTH AMERICA"}},{"match_id":6938422211,"account_id":123161333,"player_slot":4,"win":1,"profile":{"account_id":123161333,"personaname":"TheLG","avatarfull":"https://avatars.akamai.steamstatic.com/7a7626ccc78e0fb98a99d639eb9160f585a6fb15_full.jpg","loccountrycode":"SOUTH AMERICA"}},{"match_id":6938501782,"account_id":1,"player_slot":0,"win":0,"profile":{"account_id":1,"personaname":"unknown","avatarfull":"https://steamuserimages-a.akamaihd.net/ugc/885384897182110030/F095539864AC9E94AE5236E04C8CA7C2725BCEFF/","loccountrycode":"SOUTH AMERICA"}},{"match_id":6938501782,"account_id":130,"player_slot":129,"win":1,"profile":{"account_id":130,"personaname":"unknown","avatarfull":"https://steamuserimages-a.akamaihd.net/ugc/885384897182110030/F095539864AC9E94AE5236E04C8CA7C2725BCEFF/","loccountrycode":"SOUTH AMERICA"}},{"match_id":6938501782,"account_id":131,"player_slot":130,"win":1,"profile":{"account_id":131,"personaname":"unknown","avatarfull":"https://steamuserimages-a.akamaihd.net/ugc/885384897182110030/F095539864AC9E94AE5236E04C8CA7C2725BCEFF/","loccountrycode":"SOUTH AMERICA"}},{"match_id":6938501782,"account_id":132,"player_slot":131,"win":1,"profile":{"account_id":132,"personaname":"unknown","avatarfull":"https://steamuserimages-a.akamaihd.net/ugc/885384897182110030/F095539864AC9E94AE5236E04C8CA7C2725BCEFF/","loccountrycode":"SOUTH AMERICA"}},{"match_id":6938501782,"account_id":133,"player_slot":132,"win":1,"profile":{"account_id":133,"personaname":"unknown","avatarfull":"https://steamuserimages-a.akamaihd.net/ugc/885384897182110030/F095539864AC9E94AE5236E04C8CA7C2725BCEFF/","loccountrycode":"SOUTH AMERICA"}},{"match_id":6938501782,"account_id":61895929,"player_slot":2,"win":0,"profile":{"account_id":61895929,"personaname":"kimzerapqp","avatarfull":"https://avatars.akamai.steamstatic.com/3804cd416262ee8934b63067ad9f63df81115e2e_full.jpg","loccountrycode":"SOUTH AMERICA"}},{"match_id":6938501782,"account_id":87067897,"player_slot":1,"win":0,"profile":{"account_id":87067897,"personaname":"Balgus","avatarfull":"https://avatars.akamai.steamstatic.com/d0e559d0fb05b1f4c6d262356c19ea01c5e7570d_full.jpg","loccountrycode":"SOUTH AMERICA"}},{"match_id":6938501782,"account_id":96268745,"player_slot":128,"win":1,"profile":{"account_id":96268745,"personaname":"WEEZER","avatarfull":"https://avatars.akamai.steamstatic.com/8a22aad4839c7e23e357e7afa4b1f002fe481784_full.jpg","loccountrycode":"SOUTH AMERICA"}},{"match_id":6938501782,"account_id":100592368,"player_slot":3,"win":0,"profile":{"account_id":100592368,"personaname":"✪ CH ✪","avatarfull":"https://avatars.akamai.steamstatic.com/dc64eb8709bbd352b14e6232768d68f5f1256ebd_full.jpg","loccountrycode":"SOUTH AMERICA"}},{"match_id":6938501782,"account_id":123161333,"player_slot":4,"win":0,"profile":{"account_id":123161333,"personaname":"TheLG","avatarfull":"https://avatars.akamai.steamstatic.com/7a7626ccc78e0fb98a99d639eb9160f585a6fb15_full.jpg","loccountrycode":"SOUTH AMERICA"}},{"match_id":6938700821,"account_id":1,"player_slot":0,"win":0,"profile":{"account_id":1,"personaname":"unknown","avatarfull":"https://steamuserimages-a.akamaihd.net/ugc/885384897182110030/F095539864AC9E94AE5236E04C8CA7C2725BCEFF/","loccountrycode":"SOUTH AMERICA"}},{"match_id":6938700821,"account_id":3,"player_slot":2,"win":0,"profile":{"account_id":3,"personaname":"unknown","avatarfull":"https://steamuserimages-a.akamaihd.net/ugc/885384897182110030/F095539864AC9E94AE5236E04C8CA7C2725BCEFF/","loccountrycode":"SOUTH AMERICA"}},{"match_id":6938700821,"account_id":5,"player_slot":4,"win":0,"profile":{"account_id":5,"personaname":"unknown","avatarfull":"https://steamuserimages-a.akamaihd.net/ugc/885384897182110030/F095539864AC9E94AE5236E04C8CA7C2725BCEFF/","loccountrycode":"SOUTH AMERICA"}},{"match_id":6938700821,"account_id":131,"player_slot":130,"win":1,"profile":{"account_id":131,"personaname":"unknown","avatarfull":"https://steamuserimages-a.akamaihd.net/ugc/885384897182110030/F095539864AC9E94AE5236E04C8CA7C2725BCEFF/","loccountrycode":"SOUTH AMERICA"}},{"match_id":6938700821,"account_id":132,"player_slot":131,"win":1,"profile":{"account_id":132,"personaname":"unknown","avatarfull":"https://steamuserimages-a.akamaihd.net/ugc/885384897182110030/F095539864AC9E94AE5236E04C8CA7C2725BCEFF/","loccountrycode":"SOUTH AMERICA"}},{"match_id":6938700821,"account_id":67656344,"player_slot":129,"win":1,"profile":{"account_id":67656344,"personaname":"Cout","avatarfull":"https://avatars.akamai.steamstatic.com/f28b55b7f59e8634673f24e9deb840f173d7eec1_full.jpg","loccountrycode":"SOUTH AMERICA"}},{"match_id":6938700821,"account_id":86764844,"player_slot":128,"win":1,"profile":{"account_id":86764844,"personaname":"MarMosell","avatarfull":"https://avatars.akamai.steamstatic.com/febfdc238bfee83b2f31ff90d733dc11197fe890_full.jpg","loccountrycode":"SOUTH AMERICA"}},{"match_id":6938700821,"account_id":100592368,"player_slot":3,"win":0,"profile":{"account_id":100592368,"personaname":"✪ CH ✪","avatarfull":"https://avatars.akamai.steamstatic.com/dc64eb8709bbd352b14e6232768d68f5f1256ebd_full.jpg","loccountrycode":"SOUTH AMERICA"}},{"match_id":6938700821,"account_id":130155428,"player_slot":1,"win":0,"profile":{"account_id":130155428,"personaname":"FonteBoa","avatarfull":"https://avatars.akamai.steamstatic.com/5c1713360b04999b1ed70091521533597a100b5d_full.jpg","loccountrycode":"SOUTH AMERICA"}},{"match_id":6938700821,"account_id":143124306,"player_slot":132,"win":1,"profile":{"account_id":143124306,"personaname":"OhLonJhonson","avatarfull":"https://avatars.akamai.steamstatic.com/5364a10a7cfe467d63c891b56b23ae1869e285f5_full.jpg","loccountrycode":"SOUTH AMERICA"}},{"match_id":6938742405,"account_id":1,"player_slot":0,"win":0,"profile":{"account_id":1,"personaname":"unknown","avatarfull":"https://steamuserimages-a.akamaihd.net/ugc/885384897182110030/F095539864AC9E94AE5236E04C8CA7C2725BCEFF/","loccountrycode":"SOUTH AMERICA"}},{"match_id":6938742405,"account_id":5,"player_slot":4,"win":0,"profile":{"account_id":5,"personaname":"unknown","avatarfull":"https://steamuserimages-a.akamaihd.net/ugc/885384897182110030/F095539864AC9E94AE5236E04C8CA7C2725BCEFF/","loccountrycode":"SOUTH AMERICA"}},{"match_id":6938742405,"account_id":129,"player_slot":128,"win":1,"profile":{"account_id":129,"personaname":"unknown","avatarfull":"https://steamuserimages-a.akamaihd.net/ugc/885384897182110030/F095539864AC9E94AE5236E04C8CA7C2725BCEFF/","loccountrycode":"SOUTH AMERICA"}},{"match_id":6938742405,"account_id":131,"player_slot":130,"win":1,"profile":{"account_id":131,"personaname":"unknown","avatarfull":"https://steamuserimages-a.akamaihd.net/ugc/885384897182110030/F095539864AC9E94AE5236E04C8CA7C2725BCEFF/","loccountrycode":"SOUTH AMERICA"}},{"match_id":6938742405,"account_id":133,"player_slot":132,"win":1,"profile":{"account_id":133,"personaname":"unknown","avatarfull":"https://steamuserimages-a.akamaihd.net/ugc/885384897182110030/F095539864AC9E94AE5236E04C8CA7C2725BCEFF/","loccountrycode":"SOUTH AMERICA"}},{"match_id":6938742405,"account_id":100592368,"player_slot":131,"win":1,"profile":{"account_id":100592368,"personaname":"✪ CH ✪","avatarfull":"https://avatars.akamai.steamstatic.com/dc64eb8709bbd352b14e6232768d68f5f1256ebd_full.jpg","loccountrycode":"SOUTH AMERICA"}},{"match_id":6938742405,"account_id":130155428,"player_slot":129,"win":1,"profile":{"account_id":130155428,"personaname":"FonteBoa","avatarfull":"https://avatars.akamai.steamstatic.com/5c1713360b04999b1ed70091521533597a100b5d_full.jpg","loccountrycode":"SOUTH AMERICA"}},{"match_id":6938742405,"account_id":143124306,"player_slot":1,"win":0,"profile":{"account_id":143124306,"personaname":"OhLonJhonson","avatarfull":"https://avatars.akamai.steamstatic.com/5364a10a7cfe467d63c891b56b23ae1869e285f5_full.jpg","loccountrycode":"SOUTH AMERICA"}},{"match_id":6938742405,"account_id":170280782,"player_slot":2,"win":0,"profile":{"account_id":170280782,"personaname":"Hoy no es mañana","avatarfull":"https://avatars.akamai.steamstatic.com/f12cc7d93f16c6d1b07272be8b86a6700ee35e7c_full.jpg","loccountrycode":"SOUTH AMERICA"}},{"match_id":6938742405,"account_id":413728173,"player_slot":3,"win":0,"profile":{"account_id":413728173,"personaname":"CUENTA PARA FEDEAR","avatarfull":"https://avatars.akamai.steamstatic.com/c1dd88021255229d211749bed332b04227bfd4e1_full.jpg","loccountrycode":"SOUTH AMERICA"}},{"match_id":6938798596,"account_id":1,"player_slot":0,"win":1,"profile":{"account_id":1,"personaname":"unknown","avatarfull":"https://steamuserimages-a.akamaihd.net/ugc/885384897182110030/F095539864AC9E94AE5236E04C8CA7C2725BCEFF/","loccountrycode":"SOUTH AMERICA"}},{"match_id":6938798596,"account_id":2,"player_slot":1,"win":1,"profile":{"account_id":2,"personaname":"unknown","avatarfull":"https://steamuserimages-a.akamaihd.net/ugc/885384897182110030/F095539864AC9E94AE5236E04C8CA7C2725BCEFF/","loccountrycode":"SOUTH AMERICA"}},{"match_id":6938798596,"account_id":4,"player_slot":3,"win":1,"profile":{"account_id":4,"personaname":"unknown","avatarfull":"https://steamuserimages-a.akamaihd.net/ugc/885384897182110030/F095539864AC9E94AE5236E04C8CA7C2725BCEFF/","loccountrycode":"SOUTH AMERICA"}},{"match_id":6938798596,"account_id":129,"player_slot":128,"win":0,"profile":{"account_id":129,"personaname":"unknown","avatarfull":"https://steamuserimages-a.akamaihd.net/ugc/885384897182110030/F095539864AC9E94AE5236E04C8CA7C2725BCEFF/","loccountrycode":"SOUTH AMERICA"}},{"match_id":6938798596,"account_id":130,"player_slot":129,"win":0,"profile":{"account_id":130,"personaname":"unknown","avatarfull":"https://steamuserimages-a.akamaihd.net/ugc/885384897182110030/F095539864AC9E94AE5236E04C8CA7C2725BCEFF/","loccountrycode":"SOUTH AMERICA"}},{"match_id":6938798596,"account_id":132,"player_slot":131,"win":0,"profile":{"account_id":132,"personaname":"unknown","avatarfull":"https://steamuserimages-a.akamaihd.net/ugc/885384897182110030/F095539864AC9E94AE5236E04C8CA7C2725BCEFF/","loccountrycode":"SOUTH AMERICA"}},{"match_id":6938798596,"account_id":133,"player_slot":132,"win":0,"profile":{"account_id":133,"personaname":"unknown","avatarfull":"https://steamuserimages-a.akamaihd.net/ugc/885384897182110030/F095539864AC9E94AE5236E04C8CA7C2725BCEFF/","loccountrycode":"SOUTH AMERICA"}},{"match_id":6938798596,"account_id":100592368,"player_slot":4,"win":1,"profile":{"account_id":100592368,"personaname":"✪ CH ✪","avatarfull":"https://avatars.akamai.steamstatic.com/dc64eb8709bbd352b14e6232768d68f5f1256ebd_full.jpg","loccountrycode":"SOUTH AMERICA"}},{"match_id":6938798596,"account_id":130155428,"player_slot":2,"win":1,"profile":{"account_id":130155428,"personaname":"FonteBoa","avatarfull":"https://avatars.akamai.steamstatic.com/5c1713360b04999b1ed70091521533597a100b5d_full.jpg","loccountrycode":"SOUTH AMERICA"}},{"match_id":6938798596,"account_id":285739528,"player_slot":130,"win":0,"profile":{"account_id":285739528,"personaname":"†kirito†","avatarfull":"https://avatars.akamai.steamstatic.com/eee3f11eb1d47e764103ec0767b6eab09dfbc4fd_full.jpg","loccountrycode":"SOUTH AMERICA"}},{"match_id":6969186965,"account_id":1,"player_slot":0,"win":1,"profile":{"account_id":1,"personaname":"unknown","avatarfull":"https://steamuserimages-a.akamaihd.net/ugc/885384897182110030/F095539864AC9E94AE5236E04C8CA7C2725BCEFF/","loccountrycode":"SOUTH AMERICA"}},{"match_id":6969186965,"account_id":2,"player_slot":1,"win":1,"profile":{"account_id":2,"personaname":"unknown","avatarfull":"https://steamuserimages-a.akamaihd.net/ugc/885384897182110030/F095539864AC9E94AE5236E04C8CA7C2725BCEFF/","loccountrycode":"SOUTH AMERICA"}},{"match_id":6969186965,"account_id":130,"player_slot":129,"win":0,"profile":{"account_id":130,"personaname":"unknown","avatarfull":"https://steamuserimages-a.akamaihd.net/ugc/885384897182110030/F095539864AC9E94AE5236E04C8CA7C2725BCEFF/","loccountrycode":"SOUTH AMERICA"}},{"match_id":6969186965,"account_id":131,"player_slot":130,"win":0,"profile":{"account_id":131,"personaname":"unknown","avatarfull":"https://steamuserimages-a.akamaihd.net/ugc/885384897182110030/F095539864AC9E94AE5236E04C8CA7C2725BCEFF/","loccountrycode":"SOUTH AMERICA"}},{"match_id":6969186965,"account_id":132,"player_slot":131,"win":0,"profile":{"account_id":132,"personaname":"unknown","avatarfull":"https://steamuserimages-a.akamaihd.net/ugc/885384897182110030/F095539864AC9E94AE5236E04C8CA7C2725BCEFF/","loccountrycode":"SOUTH AMERICA"}},{"match_id":6969186965,"account_id":91524374,"player_slot":132,"win":0,"profile":{"account_id":91524374,"personaname":"ANTI CHUKAFLU 2.5","avatarfull":"https://avatars.akamai.steamstatic.com/7c60f459e38a9d2c80b99c8c1a39a76e4356b201_full.jpg","loccountrycode":"SOUTH AMERICA"}},{"match_id":6969186965,"account_id":100592368,"player_slot":3,"win":1,"profile":{"account_id":100592368,"personaname":"✪ CH ✪","avatarfull":"https://avatars.akamai.steamstatic.com/dc64eb8709bbd352b14e6232768d68f5f1256ebd_full.jpg","loccountrycode":"SOUTH AMERICA"}},{"match_id":6969186965,"account_id":123161333,"player_slot":2,"win":1,"profile":{"account_id":123161333,"personaname":"TheLG","avatarfull":"https://avatars.akamai.steamstatic.com/7a7626ccc78e0fb98a99d639eb9160f585a6fb15_full.jpg","loccountrycode":"SOUTH AMERICA"}},{"match_id":6969186965,"account_id":130740998,"player_slot":128,"win":0,"profile":{"account_id":130740998,"personaname":"Tupu","avatarfull":"https://avatars.akamai.steamstatic.com/466eac729065cfa41277330a2de3e00023dfaea7_full.jpg","loccountrycode":"SOUTH AMERICA"}},{"match_id":6969186965,"account_id":180327322,"player_slot":4,"win":1,"profile":{"account_id":180327322,"personaname":"Dani","avatarfull":"https://avatars.akamai.steamstatic.com/451c6ff060e12c80bb54e8bec14a729d875187d8_full.jpg","loccountrycode":"SOUTH AMERICA"}},{"match_id":6972634017,"account_id":1,"player_slot":0,"win":0,"profile":{"account_id":1,"personaname":"unknown","avatarfull":"https://steamuserimages-a.akamaihd.net/ugc/885384897182110030/F095539864AC9E94AE5236E04C8CA7C2725BCEFF/","loccountrycode":"SOUTH AMERICA"}},{"match_id":6972634017,"account_id":2,"player_slot":1,"win":0,"profile":{"account_id":2,"personaname":"unknown","avatarfull":"https://steamuserimages-a.akamaihd.net/ugc/885384897182110030/F095539864AC9E94AE5236E04C8CA7C2725BCEFF/","loccountrycode":"SOUTH AMERICA"}},{"match_id":6972634017,"account_id":129,"player_slot":128,"win":1,"profile":{"account_id":129,"personaname":"unknown","avatarfull":"https://steamuserimages-a.akamaihd.net/ugc/885384897182110030/F095539864AC9E94AE5236E04C8CA7C2725BCEFF/","loccountrycode":"SOUTH AMERICA"}},{"match_id":6972634017,"account_id":131,"player_slot":130,"win":1,"profile":{"account_id":131,"personaname":"unknown","avatarfull":"https://steamuserimages-a.akamaihd.net/ugc/885384897182110030/F095539864AC9E94AE5236E04C8CA7C2725BCEFF/","loccountrycode":"SOUTH AMERICA"}},{"match_id":6972634017,"account_id":133,"player_slot":132,"win":1,"profile":{"account_id":133,"personaname":"unknown","avatarfull":"https://steamuserimages-a.akamaihd.net/ugc/885384897182110030/F095539864AC9E94AE5236E04C8CA7C2725BCEFF/","loccountrycode":"SOUTH AMERICA"}},{"match_id":6972634017,"account_id":26032273,"player_slot":2,"win":0,"profile":{"account_id":26032273,"personaname":"Satanás","avatarfull":"https://avatars.akamai.steamstatic.com/0295339e91b8bd743b51b9303d1290c3d0c340a4_full.jpg","loccountrycode":"SOUTH AMERICA"}},{"match_id":6972634017,"account_id":51066642,"player_slot":3,"win":0,"profile":{"account_id":51066642,"personaname":"Chronaske","avatarfull":"https://avatars.akamai.steamstatic.com/f3d05db4d8557efbcdbfb337f4176abe9fcb5c1b_full.jpg","loccountrycode":"SOUTH AMERICA"}},{"match_id":6972634017,"account_id":92963050,"player_slot":4,"win":0,"profile":{"account_id":92963050,"personaname":"M3L","avatarfull":"https://avatars.akamai.steamstatic.com/d27f726bd26248f230e48c08e1c65c96faf44e4d_full.jpg","loccountrycode":"SOUTH AMERICA"}},{"match_id":6972634017,"account_id":100592368,"player_slot":131,"win":1,"profile":{"account_id":100592368,"personaname":"✪ CH ✪","avatarfull":"https://avatars.akamai.steamstatic.com/dc64eb8709bbd352b14e6232768d68f5f1256ebd_full.jpg","loccountrycode":"SOUTH AMERICA"}},{"match_id":6972634017,"account_id":123161333,"player_slot":129,"win":1,"profile":{"account_id":123161333,"personaname":"TheLG","avatarfull":"https://avatars.akamai.steamstatic.com/7a7626ccc78e0fb98a99d639eb9160f585a6fb15_full.jpg","loccountrycode":"SOUTH AMERICA"}}],"_matchIds":[6972634017,6969186965,6938798596,6938742405,6938700821,6938501782,6938422211,6938342150,6930237390,6917247754,6906995972,6906963089,6906828666,6881377114,6868427177,6868392010]}